sak1620/__init__.py
sak1620/module.py
sak1620-0.1.2.dist-info/METADATA
sak1620-0.1.2.dist-info/WHEEL
sak1620-0.1.2.dist-info/top_level.txt
sak1620-0.1.2.dist-info/RECORD
